{
  "session_id": "c427e810-5e53-4745-be75-91547dd9f1d4",
  "contract_name": "采购合同.txt",
  "created_at": "2026-03-09T09:33:39.018013",
  "updated_at": "2026-03-09T09:33:39.018013",
  "audit_result": {
    "contract_id": "C20260309-AF52",
    "metadata": {
      "processed_at": "2026-03-09T09:33:39.016899",
      "clause_count": 9,
      "party_count": 2
    },
    "parties": [
      "深圳华强北商业集团有限公司",
      "杭州东方电子科技有限公司"
    ],
    "clauses": [
      {
        "id": "第一条",
        "title": "产品清单及价格",
        "content": "甲方向乙方采购以下产品：\n\n| 序号 | 产品名称 | 规格型号 | 数量 | 单价（元） | 小计（元） |\n|------|----------|----------|------|------------|------------|\n| 1 | 笔记本电脑 | ThinkPad X1 Carbon | 50台 | 12,000 | 600,000 |\n| 2 | 台式机主机 | Dell OptiPlex 7080 | 30台 | 8,500 | 255,000 |\n| 3 | 显示器 | Dell UltraSharp 27 | 80台 | 3,200 | 256,000 |\n| 4 | 无线鼠标 | Logitech MX Master 3 | 100个 | 450 | 45,000 |\n| 5 | 机械键盘 | Keychron K8 | 80个 | 380 | 30,400 |\n\n合同总金额：人民币壹佰壹拾捌万陆仟肆佰元整（¥1,186,400.00）"
      },
      {
        "id": "第二条",
        "title": "质量标准",
        "content": "1. 乙方提供的产品必须为原装正品，符合国家相关质量标准；\n2. 产品质保期为三年，质保期内非人为损坏由乙方负责免费维修或更换；\n3. 乙方应提供产品合格证、说明书及相关配件。"
      },
      {
        "id": "第三条",
        "title": "交货时间及地点",
        "content": "1. 交货时间：合同签订后30个工作日内完成全部交货；\n2. 交货地点：甲方指定仓库（深圳市龙岗区坂田街道坂田路168号）；\n3. 运输费用及风险由乙方承担。"
      },
      {
        "id": "第四条",
        "title": "付款方式",
        "content": "1. 合同签订后5个工作日内，甲方向乙方支付合同总价的30%作为预付款，即人民币叁拾伍万伍仟玖佰贰拾元整（¥355,920.00）；\n2. 全部货物到达甲方指定地点并验收合格后5个工作日内，甲方向乙方支付合同总价的60%，即人民币柒佰壹拾壹万捌仟肆佰元整（¥711,840.00）；\n3. 质保期满后5个工作日内，甲方向乙方支付剩余10%尾款，即人民币壹拾壹万捌仟陆佰肆拾元整（¥118,640.00）。"
      },
      {
        "id": "第五条",
        "title": "验收标准",
        "content": "1. 甲方应在收到货物后15个工作日内完成验收；\n2. 验收内容：产品数量、型号、外观及功能检测；\n3. 如发现产品数量短缺、型号不符或存在质量问题，甲方有权拒收或要求乙方更换；\n4. 验收合格后，甲乙双方签署验收报告。"
      },
      {
        "id": "第六条",
        "title": "双方权利与义务",
        "content": "（一）甲方权利与义务\n1. 甲方应按合同约定及时支付货款；\n2. 甲方应配合乙方完成交货和验收工作。\n\n（二）乙方权利与义务\n1. 乙方应按合同约定的时间、数量、规格交付产品；\n2. 乙方应保证产品符合质量标准，并提供售后服务；\n3. 乙方应在交货前3个工作日通知甲方。"
      },
      {
        "id": "第七条",
        "title": "违约责任",
        "content": "1. 乙方逾期交货，每逾期一天应按合同总价款的千分之一向甲方支付违约金；\n2. 甲方逾期付款，每逾期一天应按未付款项的千分之一向乙方支付违约金；\n3. 产品质量不符合约定的，乙方应免费更换或退货，并承担因此产生的费用；\n4. 任何一方擅自解除合同，应按合同总价款的20%向对方支付违约金。"
      },
      {
        "id": "第八条",
        "title": "争议解决",
        "content": "本合同在履行过程中发生的争议，由双方协商解决；协商不成的，任何一方均有权向甲方所在地人民法院提起诉讼。"
      },
      {
        "id": "第九条",
        "title": "其他约定",
        "content": "1. 本合同一式四份，甲乙双方各执两份，具有同等法律效力；\n2. 本合同自双方签字盖章之日起生效；\n3. 未经甲方书面同意，乙方不得将本合同项下的权利义务全部或部分转让给第三方。"
      }
    ],
    "annotations": [
      {
        "id": "anno-12d21e",
        "clause_id": "第八条",
        "party": "乙方",
        "issue_type": "程序性风险",
        "description": "该条款约定争议由甲方所在地人民法院管辖。根据《中华人民共和国民事诉讼法》第三十五条，合同双方可以书面协议选择被告住所地、合同履行地、合同签订地、原告住所地、标的物所在地等与争议有实际联系的地点的人民法院管辖。虽然该约定有效，但将管辖法院固定为甲方所在地，对乙方而言，在发生争议时，将显著增加其诉讼成本（如差旅、律师费用）和应诉不便，可能构成程序上的不便利或潜在不公。",
        "severity": "中等",
        "recommendation": "建议乙方争取修改管辖条款，例如改为“向被告所在地人民法院提起诉讼”或“向合同履行地人民法院提起诉讼”，以实现双方诉讼权利的相对平衡。若无法修改，乙方应在签约前充分评估未来可能发生的争议解决成本。",
        "law_reference": "《中华人民共和国民事诉讼法》第三十五条",
        "suggested_revision": "本合同在履行过程中发生的争议，由双方协商解决；协商不成的，任何一方均有权向被告所在地人民法院提起诉讼。",
        "note": "将管辖法院由“甲方所在地”修改为“被告所在地”，符合《中华人民共和国民事诉讼法》第三十五条关于协议管辖的规定，且更符合诉讼便利原则，平衡了双方的程序性权利，避免了单方增加另一方诉讼成本与不便的风险。"
      },
      {
        "id": "anno-9f55f3",
        "clause_id": "第二条",
        "party": "乙方",
        "issue_type": "责任范围不明确",
        "description": "条款规定质保期为三年，但未明确质保期起始时间（如自交付之日、验收合格之日或安装调试完成之日起算），可能导致双方对质保期限产生争议。",
        "severity": "中等",
        "recommendation": "建议明确质保期的起算时间点，例如'自产品交付并经甲方验收合格之日起计算'。",
        "law_reference": "《中华人民共和国民法典》第六百二十二条：当事人对检验期限未作约定，买受人签收的送货单、确认单等载明标的物数量、型号、规格的，推定买受人已经对数量和外观瑕疵进行检验，但是有相关证据足以推翻的除外。",
        "suggested_revision": "1. 乙方提供的产品必须为原装正品，符合国家相关质量标准；\n2. 产品质保期为三年，自产品交付并经甲方验收合格之日起计算，质保期内非人为损坏由乙方负责免费维修或更换；\n3. 乙方应提供产品合格证、说明书及相关配件。",
        "note": "修改后的条款明确了质保期的起算时间点为'自产品交付并经甲方验收合格之日起计算'，避免了因起算时间不明确可能引发的争议，同时保留了原条款的其他内容，确保措辞合法且明确。"
      },
      {
        "id": "anno-5706fc",
        "clause_id": "第五条",
        "party": "甲方",
        "issue_type": "权利限制",
        "description": "条款规定甲方在收到货物后15个工作日内完成验收，但未明确验收期限的起算点（如自货物送达之日或签收之日），可能导致起算时间争议。此外，15个工作日可能不足以完成复杂产品的全面功能检测，若产品存在隐蔽瑕疵，甲方可能因超过此期限而丧失主张权利。",
        "severity": "中等",
        "recommendation": "建议明确验收期限的起算时间（例如“自货物送达并签收之日起”），并考虑延长验收期或增加对隐蔽瑕疵的另行约定条款，如“对于无法在验收期内发现的隐蔽质量问题，甲方可在发现后合理期限内通知乙方”",
        "law_reference": "《中华人民共和国民法典》第六百二十二条、第六百二十三条",
        "suggested_revision": "1. 甲方应在货物送达并签收之日起15个工作日内完成初步验收；对于复杂产品，如无法在初步验收期内完成全面功能检测，双方可协商延长验收期至30个工作日。验收内容包括产品数量、型号、外观及基本功能检测。\n2. 如发现产品数量短缺、型号不符或存在明显质量问题，甲方有权拒收或要求乙方更换。\n3. 验收合格后，甲乙双方应签署验收报告。\n4. 对于无法在验收期内发现的隐蔽质量问题，甲方可在发现后15个工作日内书面通知乙方，乙方应负责免费维修或更换，不受前述验收期限限制。",
        "note": "修改明确了验收期限的起算点为‘货物送达并签收之日’，避免了起算时间争议。同时，增加了对复杂产品验收期延长的协商机制，并单独约定了隐蔽质量问题的处理条款，以保护甲方在发现隐蔽瑕疵后的主张权利，使条款更全面、合法且明确。"
      },
      {
        "id": "anno-e27fbf",
        "clause_id": "第七条",
        "party": "乙方",
        "issue_type": "违约金过高风险",
        "description": "第1款约定乙方逾期交货违约金为每日千分之一（年化36.5%），可能远超实际损失。根据《民法典》及相关司法解释，约定的违约金超过造成损失的30%一般可认定为过分高于造成的损失，法院或仲裁机构可予调减。",
        "severity": "高",
        "recommendation": "建议将逾期交货违约金调整为每日万分之五或与甲方逾期付款违约金对等，并增加“违约金总额不超过合同总价款的X%”的限额条款。",
        "law_reference": "《中华人民共和国民法典》第五百八十五条；《最高人民法院关于适用<中华人民共和国民法典>合同编通则若干问题的解释》第六十五条",
        "suggested_revision": "1. 乙方逾期交货，每逾期一天应按合同总价款的万分之五向甲方支付违约金，但违约金总额累计不超过合同总价款的10%；\n2. 甲方逾期付款，每逾期一天应按未付款项的万分之五向乙方支付违约金，但违约金总额累计不超过合同总价款的10%；\n3. 产品质量不符合约定的，乙方应免费更换或退货，并承担因此产生的费用；\n4. 任何一方擅自解除合同，应按合同总价款的20%向对方支付违约金。",
        "note": "1. 将逾期交货及逾期付款的违约金标准统一调整为每日万分之五（年化约18.25%），以平衡双方权利义务，并降低被认定为过高违约金的风险。\n2. 新增违约金总额累计不超过合同总价10%的限额条款，以符合《民法典》第五百八十五条及相关司法解释关于违约金不应过分高于实际损失的原则性规定，增强条款的可执行性。\n3. 其他条款（产品质量责任、擅自解约责任）因风险描述未涉及，故予以保留。"
      },
      {
        "id": "anno-96f96d",
        "clause_id": "第四条",
        "party": "乙方",
        "issue_type": "付款条件风险",
        "description": "付款节点设置对乙方不利。预付款比例较低（30%），大部分款项（60%）需在货物到达并验收合格后支付，剩余10%尾款需在质保期满后支付。这可能导致乙方在履行合同过程中承担较大的资金压力和回款风险，特别是质保期可能较长，尾款回收时间不确定。",
        "severity": "中",
        "recommendation": "建议乙方争取提高预付款比例（例如至40%-50%），并尝试将部分款项的支付节点与发货、初步验收等更可控的环节挂钩，或缩短质保期后支付尾款的时间。",
        "law_reference": "《中华人民共和国民法典》第五百七十七条关于违约责任的规定，若甲方延迟支付，乙方可依据此条主张权利，但合同条款本身增加了乙方收款的不确定性。",
        "suggested_revision": "1. 合同签订后5个工作日内，甲方向乙方支付合同总价的40%作为预付款，即人民币肆拾柒万肆仟伍佰陆拾元整（¥474,560.00）；\n2. 全部货物生产完毕并经乙方书面通知发货后5个工作日内，甲方向乙方支付合同总价的30%，即人民币叁佰伍拾伍万玖仟贰佰元整（¥355,920.00）；\n3. 全部货物到达甲方指定地点并完成到货验收（以双方签署的《到货验收单》为准）后5个工作日内，甲方向乙方支付合同总价的20%，即人民币贰佰叁拾柒万贰仟捌佰元整（¥237,280.00）；\n4. 项目最终验收合格（以双方签署的《最终验收报告》为准）后5个工作日内，甲方向乙方支付合同总价的5%，即人民币伍拾玖万叁仟贰佰元整（¥59,320.00）；\n5. 质保期满后5个工作日内，甲方向乙方支付剩余5%尾款，即人民币伍拾玖万叁仟贰佰元整（¥59,320.00）。",
        "note": "本次修改旨在优化乙方的现金流并降低回款风险，主要调整如下：\n1. 将预付款比例从30%提高至40%，增强了项目启动阶段的资金保障。\n2. 将原验收合格后支付的60%款项拆分为多个与乙方履约进度更紧密挂钩的支付节点：\n   a. 增加“发货后”支付30%的节点，使乙方在完成主要生产义务后即可回收部分成本。\n   b. 将“到货验收合格后”支付的比例调整为20%。\n   c. 新增“最终验收合格后”支付5%的节点。\n3. 将质保期满后支付的尾款比例从10%降低至5%，缩短了尾款回收周期，减少了资金占用时间。\n4. 所有支付节点均以明确的书面文件（如通知、验收单、报告）作为触发条件，增强了可操作性和确定性。\n5. 各阶段付款金额已根据新的付款比例重新计算。"
      },
      {
        "id": "anno-3c4a9f",
        "clause_id": "第九条",
        "party": "乙方",
        "issue_type": "权利限制",
        "description": "条款规定乙方未经甲方书面同意不得转让合同权利义务，但未明确甲方在何种条件下可以拒绝同意，也未规定甲方不得无理拒绝。这可能导致乙方在需要转让时（如业务重组、融资等）受到不合理的阻碍，且缺乏救济途径。",
        "severity": "中等",
        "recommendation": "建议增加条款，明确甲方不得无理拒绝乙方的转让请求，或约定甲方应在合理期限内（如15个工作日）书面回复并说明理由，否则视为同意。同时可考虑允许乙方在特定情形下（如公司合并、分立）无需甲方同意即可转让。",
        "law_reference": "《中华人民共和国民法典》第五百四十五条：债权人可以将债权的全部或者部分转让给第三人，但是有下列情形之一的除外：（一）根据债权性质不得转让；（二）按照当事人约定不得转让；（三）依照法律规定不得转让。当事人约定非金钱债权不得转让的，不得对抗善意第三人。当事人约定金钱债权不得转让的，不得对抗第三人。",
        "suggested_revision": "3. 未经甲方事先书面同意，乙方不得将本合同项下的权利义务全部或部分转让给第三方。\n   3.1 若乙方因公司合并、分立、重组或为履行本合同项下融资安排之目的，需转让本合同权利义务的，甲方不得无理拒绝乙方的书面转让请求。乙方提出转让请求时，应向甲方提供与转让事由相关的必要证明文件。\n   3.2 甲方在收到乙方书面转让请求及相关证明文件后，应在十五（15）个工作日内书面回复。若甲方同意转让，双方应配合签署相关补充文件；若甲方不同意，应在回复中说明基于本合同履约考虑的合理理由。甲方未在前述期限内书面回复的，视为同意乙方的转让请求。\n   3.3 本条款约定的转让，不免除转让方在转让前根据本合同应承担的任何责任。\n1. 本合同一式四份，甲乙双方各执两份，具有同等法律效力；\n2. 本合同自双方签字盖章之日起生效；",
        "note": "修改后的条款在保留甲方同意权的同时，为乙方的合理转让需求提供了明确路径和保障：1) 明确了甲方不得“无理拒绝”，并列举了常见的合理转让情形（合并、分立、重组、融资）；2) 设定了甲方15个工作日的明确答复期限及“逾期视为同意”的后果，避免了甲方拖延不决；3) 要求甲方拒绝时必须说明“合理理由”，增加了甲方的审慎义务；4) 新增第3.3款，保障了合同责任在转让前后的连续性。整体修改平衡了双方权益，减少了原条款可能带来的不确定性及对乙方的不合理阻碍。"
      }
    ],
    "corrections": [
      {
        "clause_id": "第八条",
        "issue": "该条款约定争议由甲方所在地人民法院管辖。根据《中华人民共和国民事诉讼法》第三十五条，合同双方可以书面协议选择被告住所地、合同履行地、合同签订地、原告住所地、标的物所在地等与争议有实际联系的地点的人民法院管辖。虽然该约定有效，但将管辖法院固定为甲方所在地，对乙方而言，在发生争议时，将显著增加其诉讼成本（如差旅、律师费用）和应诉不便，可能构成程序上的不便利或潜在不公。",
        "suggested_revision": "本合同在履行过程中发生的争议，由双方协商解决；协商不成的，任何一方均有权向被告所在地人民法院提起诉讼。",
        "note": "将管辖法院由“甲方所在地”修改为“被告所在地”，符合《中华人民共和国民事诉讼法》第三十五条关于协议管辖的规定，且更符合诉讼便利原则，平衡了双方的程序性权利，避免了单方增加另一方诉讼成本与不便的风险。"
      },
      {
        "clause_id": "第二条",
        "issue": "条款规定质保期为三年，但未明确质保期起始时间（如自交付之日、验收合格之日或安装调试完成之日起算），可能导致双方对质保期限产生争议。",
        "suggested_revision": "1. 乙方提供的产品必须为原装正品，符合国家相关质量标准；\n2. 产品质保期为三年，自产品交付并经甲方验收合格之日起计算，质保期内非人为损坏由乙方负责免费维修或更换；\n3. 乙方应提供产品合格证、说明书及相关配件。",
        "note": "修改后的条款明确了质保期的起算时间点为'自产品交付并经甲方验收合格之日起计算'，避免了因起算时间不明确可能引发的争议，同时保留了原条款的其他内容，确保措辞合法且明确。"
      },
      {
        "clause_id": "第五条",
        "issue": "条款规定甲方在收到货物后15个工作日内完成验收，但未明确验收期限的起算点（如自货物送达之日或签收之日），可能导致起算时间争议。此外，15个工作日可能不足以完成复杂产品的全面功能检测，若产品存在隐蔽瑕疵，甲方可能因超过此期限而丧失主张权利。",
        "suggested_revision": "1. 甲方应在货物送达并签收之日起15个工作日内完成初步验收；对于复杂产品，如无法在初步验收期内完成全面功能检测，双方可协商延长验收期至30个工作日。验收内容包括产品数量、型号、外观及基本功能检测。\n2. 如发现产品数量短缺、型号不符或存在明显质量问题，甲方有权拒收或要求乙方更换。\n3. 验收合格后，甲乙双方应签署验收报告。\n4. 对于无法在验收期内发现的隐蔽质量问题，甲方可在发现后15个工作日内书面通知乙方，乙方应负责免费维修或更换，不受前述验收期限限制。",
        "note": "修改明确了验收期限的起算点为‘货物送达并签收之日’，避免了起算时间争议。同时，增加了对复杂产品验收期延长的协商机制，并单独约定了隐蔽质量问题的处理条款，以保护甲方在发现隐蔽瑕疵后的主张权利，使条款更全面、合法且明确。"
      },
      {
        "clause_id": "第七条",
        "issue": "第1款约定乙方逾期交货违约金为每日千分之一（年化36.5%），可能远超实际损失。根据《民法典》及相关司法解释，约定的违约金超过造成损失的30%一般可认定为过分高于造成的损失，法院或仲裁机构可予调减。",
        "suggested_revision": "1. 乙方逾期交货，每逾期一天应按合同总价款的万分之五向甲方支付违约金，但违约金总额累计不超过合同总价款的10%；\n2. 甲方逾期付款，每逾期一天应按未付款项的万分之五向乙方支付违约金，但违约金总额累计不超过合同总价款的10%；\n3. 产品质量不符合约定的，乙方应免费更换或退货，并承担因此产生的费用；\n4. 任何一方擅自解除合同，应按合同总价款的20%向对方支付违约金。",
        "note": "1. 将逾期交货及逾期付款的违约金标准统一调整为每日万分之五（年化约18.25%），以平衡双方权利义务，并降低被认定为过高违约金的风险。\n2. 新增违约金总额累计不超过合同总价10%的限额条款，以符合《民法典》第五百八十五条及相关司法解释关于违约金不应过分高于实际损失的原则性规定，增强条款的可执行性。\n3. 其他条款（产品质量责任、擅自解约责任）因风险描述未涉及，故予以保留。"
      },
      {
        "clause_id": "第四条",
        "issue": "付款节点设置对乙方不利。预付款比例较低（30%），大部分款项（60%）需在货物到达并验收合格后支付，剩余10%尾款需在质保期满后支付。这可能导致乙方在履行合同过程中承担较大的资金压力和回款风险，特别是质保期可能较长，尾款回收时间不确定。",
        "suggested_revision": "1. 合同签订后5个工作日内，甲方向乙方支付合同总价的40%作为预付款，即人民币肆拾柒万肆仟伍佰陆拾元整（¥474,560.00）；\n2. 全部货物生产完毕并经乙方书面通知发货后5个工作日内，甲方向乙方支付合同总价的30%，即人民币叁佰伍拾伍万玖仟贰佰元整（¥355,920.00）；\n3. 全部货物到达甲方指定地点并完成到货验收（以双方签署的《到货验收单》为准）后5个工作日内，甲方向乙方支付合同总价的20%，即人民币贰佰叁拾柒万贰仟捌佰元整（¥237,280.00）；\n4. 项目最终验收合格（以双方签署的《最终验收报告》为准）后5个工作日内，甲方向乙方支付合同总价的5%，即人民币伍拾玖万叁仟贰佰元整（¥59,320.00）；\n5. 质保期满后5个工作日内，甲方向乙方支付剩余5%尾款，即人民币伍拾玖万叁仟贰佰元整（¥59,320.00）。",
        "note": "本次修改旨在优化乙方的现金流并降低回款风险，主要调整如下：\n1. 将预付款比例从30%提高至40%，增强了项目启动阶段的资金保障。\n2. 将原验收合格后支付的60%款项拆分为多个与乙方履约进度更紧密挂钩的支付节点：\n   a. 增加“发货后”支付30%的节点，使乙方在完成主要生产义务后即可回收部分成本。\n   b. 将“到货验收合格后”支付的比例调整为20%。\n   c. 新增“最终验收合格后”支付5%的节点。\n3. 将质保期满后支付的尾款比例从10%降低至5%，缩短了尾款回收周期，减少了资金占用时间。\n4. 所有支付节点均以明确的书面文件（如通知、验收单、报告）作为触发条件，增强了可操作性和确定性。\n5. 各阶段付款金额已根据新的付款比例重新计算。"
      },
      {
        "clause_id": "第九条",
        "issue": "条款规定乙方未经甲方书面同意不得转让合同权利义务，但未明确甲方在何种条件下可以拒绝同意，也未规定甲方不得无理拒绝。这可能导致乙方在需要转让时（如业务重组、融资等）受到不合理的阻碍，且缺乏救济途径。",
        "suggested_revision": "3. 未经甲方事先书面同意，乙方不得将本合同项下的权利义务全部或部分转让给第三方。\n   3.1 若乙方因公司合并、分立、重组或为履行本合同项下融资安排之目的，需转让本合同权利义务的，甲方不得无理拒绝乙方的书面转让请求。乙方提出转让请求时，应向甲方提供与转让事由相关的必要证明文件。\n   3.2 甲方在收到乙方书面转让请求及相关证明文件后，应在十五（15）个工作日内书面回复。若甲方同意转让，双方应配合签署相关补充文件；若甲方不同意，应在回复中说明基于本合同履约考虑的合理理由。甲方未在前述期限内书面回复的，视为同意乙方的转让请求。\n   3.3 本条款约定的转让，不免除转让方在转让前根据本合同应承担的任何责任。\n1. 本合同一式四份，甲乙双方各执两份，具有同等法律效力；\n2. 本合同自双方签字盖章之日起生效；",
        "note": "修改后的条款在保留甲方同意权的同时，为乙方的合理转让需求提供了明确路径和保障：1) 明确了甲方不得“无理拒绝”，并列举了常见的合理转让情形（合并、分立、重组、融资）；2) 设定了甲方15个工作日的明确答复期限及“逾期视为同意”的后果，避免了甲方拖延不决；3) 要求甲方拒绝时必须说明“合理理由”，增加了甲方的审慎义务；4) 新增第3.3款，保障了合同责任在转让前后的连续性。整体修改平衡了双方权益，减少了原条款可能带来的不确定性及对乙方的不合理阻碍。"
      }
    ]
  }
}